Metadata-Version: 1.0
Name: GaussAndNomial-distribution
Version: 1.0.2
Summary: Gaussian and Binomial distribution
Home-page: UNKNOWN
Author: Dharmik Shah
Author-email: dharmikshah589@gmail.com
License: UNKNOWN
Platform: UNKNOWN
